devQn2/tflipflop.v
module tflipflop(q, t, clk, reset);
    output reg q;
    input t, clk, reset;

    always @(posedge clk or posedge reset) begin
        if (reset)
            q <= 1'b0;
        else if (t)
            q <= ~q;
    end
endmodule

devQn2/hellotwo.v
module hellotwo(q, enable, clk, reset);
    input enable, clk, reset;
    output [3:0] q;
    wire [3:0] t;

    assign t[0] = enable & 1'b1;                 
    assign t[1] = enable & q[0];
    assign t[2] = enable & q[0] & q[1];
    assign t[3] = enable & q[0] & q[1] & q[2];

    tflipflop tff0(q[0], t[0], clk, reset);
    tflipflop tff1(q[1], t[1], clk, reset);
    tflipflop tff2(q[2], t[2], clk, reset);
    tflipflop tff3(q[3], t[3], clk, reset);
endmodule

devQn2/dflipflop.v
module dflipflop(q, d, clk, reset);
    input d, clk, reset;
    output reg q;

    always @(posedge clk or posedge reset) begin
        if (reset)
            q <= 0;
        else
            q <= d;
    end
endmodule

devQn2/hello.v
module hello(so, pi, load, clk, reset);
    input [3:0] pi;       
    input load, clk, reset;
    output so;            

    wire q0, q1, q2, q3;  
    wire d0, d1, d2, d3;  

    assign d3 = load ? pi[3] : 1'b0;     
    assign d2 = load ? pi[2] : q3;
    assign d1 = load ? pi[1] : q2;
    assign d0 = load ? pi[0] : q1;

    dflipflop D3(q3, d3, clk, reset);
    dflipflop D2(q2, d2, clk, reset);
    dflipflop D1(q1, d1, clk, reset);
    dflipflop D0(q0, d0, clk, reset);

    assign so = q0;  
endmodule

devQn2/top.v
module top(q, so, clk, reset, load, pi);
    input clk, reset, load;
    input [3:0] pi;
    output [3:0] q;
    output so;

    hello piso_inst(so, pi, load, clk, reset);

    hellotwo counter_inst(q, so, clk, reset);

endmodule

devQn2/hello_tb.v
`timescale 1ns/1ns
`include "dflipflop.v"
`include "tflipflop.v"
`include "hello.v"
`include "hellotwo.v"
`include "top.v"

module hello_tb();
    reg clk,reset,load;
    reg [3:0]pi;
    wire so;
    wire [3:0]q;

    top Q1(q,so,clk,reset,load,pi);

    initial begin
        clk=0;
        forever #5 clk=~clk;
    end

    initial begin
    $dumpfile("hello_tb.vcd");
    $dumpvars(0, hello_tb);

    pi = 4'b0000; load = 0; reset = 1;
    #10 reset = 0;

    load = 1; pi = 4'b1011; #10;
    load = 0;               
    #80;

    load = 1; pi = 4'b1100; #10;
    load = 0;               
    #80;

    $finish;
end

endmodule

devQn2/hello_tb.vcd
$date
	Wed Nov 05 02:00:10 2025
$end
$version
	Icarus Verilog
$end
$timescale
	1ns
$end
$scope module hello_tb $end
$var wire 1 ! so $end
$var wire 4 " q [3:0] $end
$var reg 1 # clk $end
$var reg 1 $ load $end
$var reg 4 % pi [3:0] $end
$var reg 1 & reset $end
$scope module Q1 $end
$var wire 1 # clk $end
$var wire 1 $ load $end
$var wire 4 ' pi [3:0] $end
$var wire 1 & reset $end
$var wire 1 ! so $end
$var wire 4 ( q [3:0] $end
$scope module counter_inst $end
$var wire 1 # clk $end
$var wire 1 & reset $end
$var wire 4 ) t [3:0] $end
$var wire 4 * q [3:0] $end
$var wire 1 ! enable $end
$scope module tff0 $end
$var wire 1 # clk $end
$var wire 1 & reset $end
$var wire 1 + t $end
$var reg 1 , q $end
$upscope $end
$scope module tff1 $end
$var wire 1 # clk $end
$var wire 1 & reset $end
$var wire 1 - t $end
$var reg 1 . q $end
$upscope $end
$scope module tff2 $end
$var wire 1 # clk $end
$var wire 1 & reset $end
$var wire 1 / t $end
$var reg 1 0 q $end
$upscope $end
$scope module tff3 $end
$var wire 1 # clk $end
$var wire 1 & reset $end
$var wire 1 1 t $end
$var reg 1 2 q $end
$upscope $end
$upscope $end
$scope module piso_inst $end
$var wire 1 # clk $end
$var wire 1 $ load $end
$var wire 4 3 pi [3:0] $end
$var wire 1 & reset $end
$var wire 1 ! so $end
$var wire 1 4 q3 $end
$var wire 1 5 q2 $end
$var wire 1 6 q1 $end
$var wire 1 7 q0 $end
$var wire 1 8 d3 $end
$var wire 1 9 d2 $end
$var wire 1 : d1 $end
$var wire 1 ; d0 $end
$scope module D0 $end
$var wire 1 # clk $end
$var wire 1 ; d $end
$var wire 1 & reset $end
$var reg 1 7 q $end
$upscope $end
$scope module D1 $end
$var wire 1 # clk $end
$var wire 1 : d $end
$var wire 1 & reset $end
$var reg 1 6 q $end
$upscope $end
$scope module D2 $end
$var wire 1 # clk $end
$var wire 1 9 d $end
$var wire 1 & reset $end
$var reg 1 5 q $end
$upscope $end
$scope module D3 $end
$var wire 1 # clk $end
$var wire 1 8 d $end
$var wire 1 & reset $end
$var reg 1 4 q $end
$upscope $end
$upscope $end
$upscope $end
$upscope $end
$enddefinitions $end
$comment Show the parameter values. $end
$dumpall
$end
#0
$dumpvars
0;
0:
09
08
07
06
05
04
b0 3
02
01
00
0/
0.
0-
0,
0+
b0 *
b0 )
b0 (
b0 '
1&
b0 %
0$
0#
b0 "
0!
$end
#5
1#
#10
18
1:
1;
0#
b1011 %
b1011 '
b1011 3
1$
0&
#15
1+
b1 )
14
16
1!
17
1#
#20
08
19
0:
0#
0$
#25
1-
b11 )
0;
1:
09
b1 "
b1 (
b1 *
1,
06
15
04
1#
#30
0#
#35
0-
0+
0:
1;
b0 )
05
16
0!
07
0,
b10 "
b10 (
b10 *
1.
1#
#40
0#
#45
1+
b1 )
0;
1!
17
06
1#
#50
0#
#55
0+
b0 )
0!
07
b11 "
b11 (
b11 *
1,
1#
#60
0#
#65
1#
#70
0#
#75
1#
#80
0#
#85
1#
#90
0#
#95
1#
#100
19
18
0:
0;
0#
b1100 %
b1100 '
b1100 3
1$
#105
15
14
1#
#110
08
1:
0#
0$
#115
09
1;
04
16
1#
#120
0#
#125
1/
1-
1+
b111 )
0:
1!
17
05
1#
#130
0#
#135
0-
0/
01
b1 )
0;
06
0,
0.
b100 "
b100 (
b100 *
10
1#
#140
0#
#145
0+
b0 )
b101 "
b101 (
b101 *
1,
0!
07
1#
