eighttooneMUX/fourtooneMUX.v
module fourtooneMUX(y,i,s);
    input [3:0]i;
    input [1:0]s;
    output reg y;

    always @(*) begin
       case(s)
       2'b00: y=i[0]; 
       2'b01: y=i[1]; 
       2'b10: y=i[2]; 
       2'b11: y=i[3];
       default: y=i[0]; 
       endcase
    end
endmodule

eighttooneMUX/twotooneMUX.v
module twotooneMUX(y,i,s0);
    input [1:0]i;
    input s0;
    output y;

    assign y=(s0?i[1]:i[0]);
endmodule

eighttooneMUX/eighttooneMUX.v
module eighttooneMUX(y,i,s);
    input [7:0]i;
    input [2:0]s;
    output y;

    wire [4:0] temp;

    twotooneMUX t0(temp[0], i[1:0],s[0]);
    twotooneMUX t1(temp[1], i[3:2],s[0]);
    twotooneMUX t2(temp[2], i[5:4],s[0]);
    twotooneMUX t3(temp[3], i[7:6],s[0]);

    fourtooneMUX f1(temp[4], temp[3:0], s[2:1]);

    assign y=temp[4];
endmodule

eighttooneMUX/eighttooneMUX_tb.v
`timescale 1ns/1ns
`include "twotooneMUX.v"
`include "fourtooneMUX.v"
`include "eighttooneMUX.v"

module eighttooneMUX_tb();
    reg [7:0]i;
    reg [2:0]s;
    wire y;

    eighttooneMUX Q1(y,i,s);

    initial begin
        $dumpfile("eighttooneMUX_tb.vcd");
        $dumpvars(0, eighttooneMUX_tb);

        i = 8'b11100101; s = 4'b0000; #10;
        s = 4'b0001; #10;
        s = 4'b0010; #10;
        s = 4'b0011; #10;
        s = 4'b0100; #10;
        s = 4'b0101; #10;
        s = 4'b0110; #10;
        s = 4'b0111; #10;

        $finish;
    end
endmodule

eighttooneMUX/eighttooneMUX_tb.vcd
$date
	Wed Nov 05 11:21:59 2025
$end
$version
	Icarus Verilog
$end
$timescale
	1ns
$end
$scope module eighttooneMUX_tb $end
$var wire 1 ! y $end
$var reg 8 " i [7:0] $end
$var reg 3 # s [2:0] $end
$scope module Q1 $end
$var wire 8 $ i [7:0] $end
$var wire 3 % s [2:0] $end
$var wire 1 ! y $end
$var wire 5 & temp [4:0] $end
$scope module f1 $end
$var wire 4 ' i [3:0] $end
$var wire 2 ( s [1:0] $end
$var reg 1 ) y $end
$upscope $end
$scope module t0 $end
$var wire 2 * i [1:0] $end
$var wire 1 + s0 $end
$var wire 1 , y $end
$upscope $end
$scope module t1 $end
$var wire 2 - i [1:0] $end
$var wire 1 . s0 $end
$var wire 1 / y $end
$upscope $end
$scope module t2 $end
$var wire 2 0 i [1:0] $end
$var wire 1 1 s0 $end
$var wire 1 2 y $end
$upscope $end
$scope module t3 $end
$var wire 2 3 i [1:0] $end
$var wire 1 4 s0 $end
$var wire 1 5 y $end
$upscope $end
$upscope $end
$upscope $end
$enddefinitions $end
$comment Show the parameter values. $end
$dumpall
$end
#0
$dumpvars
15
04
b11 3
02
01
b10 0
1/
0.
b1 -
1,
0+
b1 *
1)
b0 (
b1011 '
b11011 &
b0 %
b11100101 $
b0 #
b11100101 "
1!
$end
#10
0!
0)
b1100 '
0,
0/
b1100 &
12
1+
1.
11
14
b1 #
b1 %
#20
1!
1)
b1011 '
1,
1/
b11011 &
02
0+
0.
01
04
b1 (
b10 #
b10 %
#30
0!
0)
b1100 '
0,
0/
b1100 &
12
1+
1.
11
14
b11 #
b11 %
#40
b1011 '
0!
1,
1/
02
b1011 &
0)
0+
0.
01
04
b10 (
b100 #
b100 %
#50
1!
1)
b1100 '
0,
0/
b11100 &
12
1+
1.
11
14
b101 #
b101 %
#60
b1011 '
1,
1/
b11011 &
02
0+
0.
01
04
b11 (
b110 #
b110 %
#70
b1100 '
0,
0/
b11100 &
12
1+
1.
11
14
b111 #
b111 %
