counter/SynchrousCounter/batch1Qn/tflipflop.v
module tflipflop(q, t, clk, reset);
    input t, clk, reset;
    output reg q;

    always @(posedge clk or posedge reset) begin
        if (reset)
            q <= 0;
        else if (t)
            q <= ~q;
    end
endmodule

counter/SynchrousCounter/batch1Qn/hello.v
module hello(y,q,clk,reset);
    input clk, reset;
    output reg y;
    output [3:0] q;
    wire [3:0] t;

    assign t[0] = 1'b1;                 
    assign t[1] = q[0];
    assign t[2] = q[0] & q[1];
    assign t[3] = q[0] & q[1] & q[2];

    tflipflop tff0(q[0], t[0], clk, reset);
    tflipflop tff1(q[1], t[1], clk, reset);
    tflipflop tff2(q[2], t[2], clk, reset);
    tflipflop tff3(q[3], t[3], clk, reset);

    always @(*) begin
        if (q == 4'b0011 || q == 4'b1001)
            y = 1'b1;
        else
            y = 1'b0;
    end
endmodule

counter/SynchrousCounter/batch1Qn/design_tb.v
`timescale 1ns/1ns
`include "tflipflop.v"
`include "hello.v"

module design_tb;
    reg clk, reset;
    wire [3:0] q;
    wire y;

    hello Q1(y, q, clk, reset);

    initial begin
        clk = 0;
        forever #5 clk = ~clk;
    end

    initial begin
        $dumpfile("design_tb.vcd");
        $dumpvars(0, design_tb);

        reset = 1;
        #10 reset = 0;

        #200 $finish;
    end
endmodule

counter/SynchrousCounter/batch1Qn/design_tb.vcd
$date
	Tue Nov 04 20:25:44 2025
$end
$version
	Icarus Verilog
$end
$timescale
	1ns
$end
$scope module design_tb $end
$var wire 1 ! y $end
$var wire 4 " q [3:0] $end
$var reg 1 # clk $end
$var reg 1 $ reset $end
$scope module Q1 $end
$var wire 1 # clk $end
$var wire 1 $ reset $end
$var wire 4 % t [3:0] $end
$var wire 4 & q [3:0] $end
$var reg 1 ! y $end
$scope module tff0 $end
$var wire 1 # clk $end
$var wire 1 $ reset $end
$var wire 1 ' t $end
$var reg 1 ( q $end
$upscope $end
$scope module tff1 $end
$var wire 1 # clk $end
$var wire 1 $ reset $end
$var wire 1 ) t $end
$var reg 1 * q $end
$upscope $end
$scope module tff2 $end
$var wire 1 # clk $end
$var wire 1 $ reset $end
$var wire 1 + t $end
$var reg 1 , q $end
$upscope $end
$scope module tff3 $end
$var wire 1 # clk $end
$var wire 1 $ reset $end
$var wire 1 - t $end
$var reg 1 . q $end
$upscope $end
$upscope $end
$upscope $end
$enddefinitions $end
$comment Show the parameter values. $end
$dumpall
$end
#0
$dumpvars
0.
0-
0,
0+
0*
0)
0(
1'
b0 &
b1 %
1$
0#
b0 "
0!
$end
#5
1#
#10
0#
0$
#15
1)
b11 %
b1 "
b1 &
1(
1#
#20
0#
#25
0)
b1 %
1*
b10 "
b10 &
0(
1#
#30
0#
#35
1+
1)
b111 %
1!
b11 "
b11 &
1(
1#
#40
0#
#45
0+
0)
b1 %
0!
1,
0*
b100 "
b100 &
0(
1#
#50
0#
#55
1)
b11 %
b101 "
b101 &
1(
1#
#60
0#
#65
0)
b1 %
1*
b110 "
b110 &
0(
1#
#70
0#
#75
1-
1+
1)
b1111 %
b111 "
b111 &
1(
1#
#80
0#
#85
0-
0+
0)
b1 %
1.
0,
0*
b1000 "
b1000 &
0(
1#
#90
0#
#95
1)
b11 %
1!
b1001 "
b1001 &
1(
1#
#100
0#
#105
0)
b1 %
0!
1*
b1010 "
b1010 &
0(
1#
#110
0#
#115
1+
1)
b111 %
b1011 "
b1011 &
1(
1#
#120
0#
#125
0+
0)
b1 %
1,
0*
b1100 "
b1100 &
0(
1#
#130
0#
#135
1)
b11 %
b1101 "
b1101 &
1(
1#
#140
0#
#145
0)
b1 %
1*
b1110 "
b1110 &
0(
1#
#150
0#
#155
1-
1+
1)
b1111 %
b1111 "
b1111 &
1(
1#
#160
0#
#165
0-
0+
0)
b1 %
0.
0,
0*
b0 "
b0 &
0(
1#
#170
0#
#175
1)
b11 %
b1 "
b1 &
1(
1#
#180
0#
#185
0)
b1 %
1*
b10 "
b10 &
0(
1#
#190
0#
#195
1+
1)
b111 %
1!
b11 "
b11 &
1(
1#
#200
0#
#205
0+
0)
b1 %
0!
1,
0*
b100 "
b100 &
0(
1#
