designQn2/pipo.v
module pipo(po,so,pi,clk,reset);
    input clk,reset;
    output so;
    output reg [3:0] po;
    input [3:0] pi;

    always @ (posedge clk or posedge reset) begin
        if(reset) po<=4'b0000;
        else begin
            po<=pi;
        end
    end

    assign so=po[0];
endmodule

designQn2/mux.v
module mux (y,s,a,b);
    input s;
    input [3:0] a,b;
    output [3:0]y;

    assign y=s?a:b;
endmodule

designQn2/subtractor.v
module fullAdder(sum,cout,a,b,cin);
    input a,b,cin;
    output sum,cout;

    assign sum=a^b^cin;
    assign cout=(a&b)|(a&cin)|(b&cin);

endmodule

module subtractor(flag, a, b);
    input [3:0] a,b;
    output flag;

    wire [3:0] sum;
    wire [3:0] c;

    wire n;
    wire v;
    wire zero;

    wire [3:0]bn;

    assign bn[0]=~b[0];
    assign bn[1]=~b[1];
    assign bn[2]=~b[2];
    assign bn[3]=~b[3];

    fullAdder fa0(sum[0],c[0],a[0],bn[0],1'b1);
    fullAdder fa1(sum[1],c[1],a[1],bn[1],c[0]);
    fullAdder fa2(sum[2],c[2],a[2],bn[2],c[1]);
    fullAdder fa3(sum[3],c[3],a[3],bn[3],c[2]);

    assign n=sum[3];
    assign v=c[2]^c[3];

    assign flag=n^v;

endmodule

designQn2/hello.v
module hello(q,a,b,clk,reset);
    input clk, reset;
    input [3:0] a,b;
    output [3:0] q;
    wire flag;
    wire [3:0] temp;
    wire so;


    subtractor s(flag, a, b);
    mux m(temp,flag,a,b);
    pipo p(q,so,temp,clk,reset);

endmodule

designQn2/hello_tb.v
`timescale 1ns/1ns
`include "pipo.v"
`include "mux.v"
`include "subtractor.v"
`include "hello.v"

module hello_tb();
    // Declare a and b as signed registers
    reg clk, reset;
    reg signed [3:0] a,b; // Declaring inputs as signed
    wire signed [3:0] q; // Declaring output as signed

    hello Q1(q,a,b,clk,reset);

    initial begin
        clk=0;
        forever #5 clk=~clk;
    end

    initial begin
        $dumpfile("hello_tb.vcd");
        $dumpvars(0, hello_tb);

        // All values are within the 4-bit signed range (-8 to 7)

        a=5; b=-2; reset=1; // 5 and -2
        #10 reset=0;
        #20 a=-7; b=5;      // -7 and 5
        #20 a=6; b=3;       // 6 and 3
        #20 a=-6; b=-4;     // -6 and -4
        #20 a=7; b=-8;      // 7 and -8
        #20 a=0; b=0;       // Test equality
        #20 a=-1; b=1;      // -1 and 1

        $finish;
    end

endmodule

designQn2/hello_tb.vcd
$date
	Thu Nov 06 01:52:16 2025
$end
$version
	Icarus Verilog
$end
$timescale
	1ns
$end
$scope module hello_tb $end
$var wire 4 ! q [3:0] $end
$var reg 4 " a [3:0] $end
$var reg 4 # b [3:0] $end
$var reg 1 $ clk $end
$var reg 1 % reset $end
$scope module Q1 $end
$var wire 4 & a [3:0] $end
$var wire 4 ' b [3:0] $end
$var wire 1 $ clk $end
$var wire 1 % reset $end
$var wire 4 ( temp [3:0] $end
$var wire 1 ) so $end
$var wire 4 * q [3:0] $end
$var wire 1 + flag $end
$scope module m $end
$var wire 4 , a [3:0] $end
$var wire 4 - b [3:0] $end
$var wire 4 . y [3:0] $end
$var wire 1 + s $end
$upscope $end
$scope module p $end
$var wire 1 $ clk $end
$var wire 4 / pi [3:0] $end
$var wire 1 % reset $end
$var wire 1 ) so $end
$var reg 4 0 po [3:0] $end
$upscope $end
$scope module s $end
$var wire 4 1 a [3:0] $end
$var wire 4 2 b [3:0] $end
$var wire 1 + flag $end
$var wire 1 3 v $end
$var wire 4 4 sum [3:0] $end
$var wire 1 5 n $end
$var wire 4 6 c [3:0] $end
$var wire 4 7 bn [3:0] $end
$scope module fa0 $end
$var wire 1 8 a $end
$var wire 1 9 b $end
$var wire 1 : cin $end
$var wire 1 ; cout $end
$var wire 1 < sum $end
$upscope $end
$scope module fa1 $end
$var wire 1 = a $end
$var wire 1 > b $end
$var wire 1 ? cin $end
$var wire 1 @ cout $end
$var wire 1 A sum $end
$upscope $end
$scope module fa2 $end
$var wire 1 B a $end
$var wire 1 C b $end
$var wire 1 D cin $end
$var wire 1 E cout $end
$var wire 1 F sum $end
$upscope $end
$scope module fa3 $end
$var wire 1 G a $end
$var wire 1 H b $end
$var wire 1 I cin $end
$var wire 1 J cout $end
$var wire 1 K sum $end
$upscope $end
$upscope $end
$upscope $end
$upscope $end
$enddefinitions $end
$comment Show the parameter values. $end
$dumpall
$end
#0
$dumpvars
0K
0J
0I
0H
0G
1F
0E
0D
0C
1B
1A
0@
1?
0>
0=
1<
1;
1:
19
18
b1 7
b1 6
05
b111 4
03
b1110 2
b101 1
b0 0
b1110 /
b1110 .
b1110 -
b101 ,
0+
b0 *
0)
b1110 (
b1110 '
b101 &
1%
0$
b1110 #
b101 "
b0 !
$end
#5
1$
#10
0$
0%
#15
b1110 !
b1110 *
b1110 0
1$
#20
0$
#25
1$
#30
13
1D
1J
0<
0A
b1011 6
1@
1+
05
09
1>
1H
1F
b100 4
0K
b1010 7
b1001 (
b1001 .
b1001 /
0B
1G
0$
b101 #
b101 '
b101 -
b101 2
b1001 "
b1001 &
b1001 ,
b1001 1
#35
1)
b1001 !
b1001 *
b1001 0
1$
#40
0$
#45
1$
#50
0D
03
0@
0?
1I
0+
0;
1E
05
b1100 6
1J
0>
1C
1<
1A
0F
b11 4
0K
b1100 7
b11 (
b11 .
b11 /
08
1=
1B
0G
0$
b11 #
b11 '
b11 -
b11 2
b110 "
b110 &
b110 ,
b110 1
#55
b11 !
b11 *
b11 0
1$
#60
0$
#65
1$
#70
0J
1D
1?
1@
03
0<
1;
1A
0I
1+
b11 6
0E
15
19
1>
0C
0H
1F
b1110 4
1K
b11 7
b1010 (
b1010 .
b1010 /
0B
1G
0$
b1100 #
b1100 '
b1100 -
b1100 2
b1010 "
b1010 &
b1010 ,
b1010 1
#75
0)
b1010 !
b1010 *
b1010 0
1$
#80
0$
#85
1$
#90
13
1I
0+
b111 6
1E
15
1C
1<
1F
b1111 4
1K
b111 7
b1000 (
b1000 .
b1000 /
18
1B
0G
0$
b1000 #
b1000 '
b1000 -
b1000 2
b111 "
b111 &
b111 ,
b111 1
#95
b1000 !
b1000 *
b1000 0
1$
#100
0$
#105
1$
#110
03
05
0K
b1111 6
1J
1H
0<
0A
b0 4
0F
b1111 7
b0 (
b0 .
b0 /
08
0=
0B
0$
b0 #
b0 '
b0 -
b0 2
b0 "
b0 &
b0 ,
b0 1
#115
b0 !
b0 *
b0 0
1$
#120
0$
#125
1$
#130
1+
15
09
0<
1A
1F
b1110 4
1K
b1110 7
b1111 (
b1111 .
b1111 /
18
1=
1B
1G
0$
b1 #
b1 '
b1 -
b1 2
b1111 "
b1111 &
b1111 ,
b1111 1
