kamleshQn1/tflipflop.v
module tflipflop(q,t,clk,reset);
    input t,clk,reset;
    output reg q;

    always @ (posedge clk or posedge reset) begin
        if(reset) begin
            q<=0;
        end else begin
            if(t==1) q<=~q;
            else q<=q;
        end
    end
endmodule

kamleshQn1/helloone.v
// asynchrous up counter

module helloone(q,clk,reset,val);
    input clk,reset,val;
    output [1:0]q;

    wire temp;

    assign temp=val?~q[0]:q[0];


    tflipflop tff1(q[0],1'b1,clk,reset);
    tflipflop tff2(q[1],1'b1,temp,reset);

endmodule

kamleshQn1/hello.v
// subtractor

module fulladder(y,cout,a,b,cin);
    input a,b,cin;
    output y,cout;

    assign y=a^b^cin;
    assign cout=(a&b)|(a&cin)|(b&cin);

endmodule


module fourbitadder(y,cout,a,b,cin);
    input [3:0] a,b;
    input cin;
    output [3:0] y;
    output cout;

    wire [2:0] temp;

    fulladder fa0(y[0],temp[0],a[0],b[0],cin);
    fulladder fa1(y[1],temp[1],a[1],b[1],temp[0]);
    fulladder fa2(y[2],temp[2],a[2],b[2],temp[1]);
    fulladder fa3(y[3],cout,a[3],b[3],temp[2]);

endmodule


module hello(y,cout,val,a,b);
    input [3:0] a,b;
    output [3:0] y;
    output cout,val;

    fourbitadder f1(y,cout,a,~b,1'b1);

    assign val=(y<5?1:0);
endmodule

kamleshQn1/top.v
// top module connecting everyhting
module top(q,a,b,clk,reset);
    input [3:0]a,b;
    input clk,reset;
    output [1:0] q;
    
    wire [3:0] temp1;
    wire t1;
    wire val;

    hello h1(temp1,t1,val,a,b);
    helloone h2(q,clk,reset,val);

endmodule

kamleshQn1/hello_tb.v
`timescale 1ns/1ns
`include "tflipflop.v"
`include "hello.v"
`include "helloone.v"
`include "top.v"

module hello_tb();
    reg [3:0]a,b;
    reg clk,reset;
    wire [1:0] q;

    top Q1(q,a,b,clk,reset);

    initial begin
        clk=0;
        forever #5 clk=~clk;
    end

    initial begin
        $dumpfile("hello_tb.vcd");
        $dumpvars(0, hello_tb);

        a=10;b=5;reset=1;

        #10 reset=0;
        #10 a=11; b=9;
        #10 a=9;b=1;
        #10 a=10;b=1;
        #10 a=7;b=5;

        $finish;

    end
endmodule

kamleshQn1/hello_tb.vcd
$date
	Wed Nov 05 20:04:20 2025
$end
$version
	Icarus Verilog
$end
$timescale
	1ns
$end
$scope module hello_tb $end
$var wire 2 ! q [1:0] $end
$var reg 4 " a [3:0] $end
$var reg 4 # b [3:0] $end
$var reg 1 $ clk $end
$var reg 1 % reset $end
$scope module Q1 $end
$var wire 4 & a [3:0] $end
$var wire 4 ' b [3:0] $end
$var wire 1 $ clk $end
$var wire 1 % reset $end
$var wire 1 ( val $end
$var wire 4 ) temp1 [3:0] $end
$var wire 1 * t1 $end
$var wire 2 + q [1:0] $end
$scope module h1 $end
$var wire 4 , a [3:0] $end
$var wire 4 - b [3:0] $end
$var wire 4 . y [3:0] $end
$var wire 1 ( val $end
$var wire 1 * cout $end
$scope module f1 $end
$var wire 4 / a [3:0] $end
$var wire 4 0 b [3:0] $end
$var wire 1 1 cin $end
$var wire 4 2 y [3:0] $end
$var wire 3 3 temp [2:0] $end
$var wire 1 * cout $end
$scope module fa0 $end
$var wire 1 4 a $end
$var wire 1 5 b $end
$var wire 1 1 cin $end
$var wire 1 6 cout $end
$var wire 1 7 y $end
$upscope $end
$scope module fa1 $end
$var wire 1 8 a $end
$var wire 1 9 b $end
$var wire 1 : cin $end
$var wire 1 ; cout $end
$var wire 1 < y $end
$upscope $end
$scope module fa2 $end
$var wire 1 = a $end
$var wire 1 > b $end
$var wire 1 ? cin $end
$var wire 1 @ cout $end
$var wire 1 A y $end
$upscope $end
$scope module fa3 $end
$var wire 1 B a $end
$var wire 1 C b $end
$var wire 1 D cin $end
$var wire 1 * cout $end
$var wire 1 E y $end
$upscope $end
$upscope $end
$upscope $end
$scope module h2 $end
$var wire 1 $ clk $end
$var wire 1 % reset $end
$var wire 1 ( val $end
$var wire 1 F temp $end
$var wire 2 G q [1:0] $end
$scope module tff1 $end
$var wire 1 $ clk $end
$var wire 1 % reset $end
$var wire 1 H t $end
$var reg 1 I q $end
$upscope $end
$scope module tff2 $end
$var wire 1 F clk $end
$var wire 1 % reset $end
$var wire 1 J t $end
$var reg 1 K q $end
$upscope $end
$upscope $end
$upscope $end
$upscope $end
$enddefinitions $end
$comment Show the parameter values. $end
$dumpall
$end
#0
$dumpvars
0K
1J
0I
1H
b0 G
0F
0E
0D
1C
1B
1A
0@
1?
0>
0=
0<
1;
0:
19
18
17
06
05
04
b10 3
b101 2
11
b1010 0
b1010 /
b101 .
b101 -
b1010 ,
b0 +
1*
b101 )
0(
b101 '
b1010 &
1%
0$
b101 #
b1010 "
b0 !
$end
#5
1$
#10
0$
0%
#15
1K
1F
b11 !
b11 +
b11 G
1I
1$
#20
b1 !
b1 +
b1 G
0K
0F
1<
1D
1*
1(
1:
0A
1@
0E
b111 3
16
b10 )
b10 .
b10 2
07
1>
0C
b110 0
14
0$
b1001 #
b1001 '
b1001 -
b1011 "
b1011 &
b1011 ,
b1011 /
#25
1K
1F
b10 !
b10 +
b10 G
0I
1$
#30
0F
0(
1E
b1000 )
b1000 .
b1000 2
0<
1C
b1110 0
08
0$
b1 #
b1 '
b1 -
b1001 "
b1001 &
b1001 ,
b1001 /
#35
0K
1F
b1 !
b1 +
b1 G
1I
1$
#40
0:
b110 3
06
17
b1001 )
b1001 .
b1001 2
0<
04
18
0$
b1010 "
b1010 &
b1010 ,
b1010 /
#45
0F
b0 !
b0 +
b0 G
0I
1$
#50
b10 !
b10 +
b10 G
1K
1<
1F
1:
1(
b111 3
16
07
0A
b10 )
b10 .
b10 2
0E
0>
b1010 0
14
1=
0B
0$
b101 #
b101 '
b101 -
b111 "
b111 &
b111 ,
b111 /
