designQn1/jkflipflop.v
//Write behavioral Verilog code for a positive edge-triggered JK FF with synchronous active
//high reset

module jkflipflop(q,j,k,clk,reset);
    input j,k,clk, reset;
    output reg q;


    always @(posedge clk) begin
        if(reset==1'b1) begin
            q<=1'b0;
        end
        else begin
            case ({j,k})
            2'b00: q<=q;
            2'b10: q<=1'b1;
            2'b01: q<=1'b0;
            2'b11: q<=~q;
            default:q<=q;
            endcase
        end
    end
endmodule

designQn1/designQ1.v
module designQ1(q,a,b,e,x,clk,reset);
    input a,b,e,clk,x,reset;
    output [1:0]q;
    wire ja,ka,jb,kb;

    assign ja=e&(b&x|~b&~x);
    assign ka=ja;
    assign jb=e;
    assign kb=e;

    jkflipflop jk1(q[1], ja, ka, clk, reset);
    jkflipflop jk2(q[0], jb, kb, clk, reset);
    
endmodule

designQn1/designQ1_tb.v
`include "jkflipflop.v"
`include "designQ1.v"
`timescale 1ns/1ns

module designQ1_tb();
    reg a,b,e,x,clk,reset;
    wire [1:0]q;

    designQ1 Q1(q,a,b,e,x,clk,reset);

    initial begin
        clk=0;
        forever #5 clk=~clk;
    end

    initial begin 
        $dumpfile("designQ1_tb.vcd");
        $dumpvars(0, designQ1_tb);

        a=0;b=0;e=0;x=0;reset=1;

        #10 reset=0;
        
        #10 e=1;x=1;a=0;b=0;
        #20 a=1;x=0;b=0;
        #20 a=0;x=1;b=1;
        #20 a=1;x=0;b=1;
        #20 e=0;x=1;a=1;b=0;
        #20 e=0;x=0;a=0;b=0;
        #20 e=0;x=0;a=0;b=1;

        
    $finish;
    end
endmodule

designQn1/designQ1_tb.vcd
$date
	Tue Nov 04 18:37:50 2025
$end
$version
	Icarus Verilog
$end
$timescale
	1ns
$end
$scope module designQ1_tb $end
$var wire 2 ! q [1:0] $end
$var reg 1 " a $end
$var reg 1 # b $end
$var reg 1 $ clk $end
$var reg 1 % e $end
$var reg 1 & reset $end
$var reg 1 ' x $end
$scope module Q1 $end
$var wire 1 " a $end
$var wire 1 # b $end
$var wire 1 $ clk $end
$var wire 1 % e $end
$var wire 1 ( ja $end
$var wire 1 ) jb $end
$var wire 1 * ka $end
$var wire 1 + kb $end
$var wire 1 & reset $end
$var wire 1 ' x $end
$var wire 2 , q [1:0] $end
$scope module jk1 $end
$var wire 1 $ clk $end
$var wire 1 ( j $end
$var wire 1 * k $end
$var wire 1 & reset $end
$var reg 1 - q $end
$upscope $end
$scope module jk2 $end
$var wire 1 $ clk $end
$var wire 1 ) j $end
$var wire 1 + k $end
$var wire 1 & reset $end
$var reg 1 . q $end
$upscope $end
$upscope $end
$upscope $end
$enddefinitions $end
$comment Show the parameter values. $end
$dumpall
$end
#0
$dumpvars
x.
x-
bx ,
0+
0*
0)
0(
0'
1&
0%
0$
0#
0"
bx !
$end
#5
0-
b0 !
b0 ,
0.
1$
#10
0$
0&
#15
1$
#20
0*
0(
0$
1'
1)
1+
1%
#25
b1 !
b1 ,
1.
1$
#30
0$
#35
b0 !
b0 ,
0.
1$
#40
1*
1(
0$
0'
1"
#45
1-
b11 !
b11 ,
1.
1$
#50
0$
#55
0.
b0 !
b0 ,
0-
1$
#60
0$
1#
1'
0"
#65
1-
b11 !
b11 ,
1.
1$
#70
0$
#75
0.
b0 !
b0 ,
0-
1$
#80
0*
0(
0$
0'
1"
#85
b1 !
b1 ,
1.
1$
#90
0$
#95
b0 !
b0 ,
0.
1$
#100
0$
0#
1'
0)
0+
0%
#105
1$
#110
0$
#115
1$
#120
0$
0"
0'
#125
1$
#130
0$
#135
1$
#140
0$
1#
