devQn1/dflipflop.v
module dflipflop(q, d, clk, resetn);
    input d, clk, resetn;
    output reg q;

    always @(posedge clk or negedge resetn) begin
        if (~resetn)
            q <= 0;
        else
            q <= d;
    end
endmodule

devQn1/hello.v
module hello(po,so,y,clk,resetn,si);
    input clk, resetn, si;
    output [3:0]po;
    output so,y;

    wire [3:0] temp;

    dflipflop d3(temp[3],si,clk,resetn);
    dflipflop d2(temp[2],temp[3],clk,resetn);
    dflipflop d1(temp[1],temp[2],clk,resetn);
    dflipflop d0(temp[0],temp[1],clk,resetn);

    assign so=temp[0];

    assign po=temp;

    assign y=~temp[3]|~temp[2]&~temp[1];

endmodule

devQn1/hello_tb.v
`timescale 1ns/1ns
`include "dflipflop.v"
`include "hello.v"


module hello_tb();
    reg clk,resetn,si;
    wire [3:0]po;
    wire so,y;

    hello Q1(po,so,y,clk,resetn,si);

    initial begin
        clk=0;
        forever #5 clk=~clk;
    end

    initial begin
        $dumpfile("hello_tb.vcd");
        $dumpvars(0, hello_tb);

        resetn=0;

        #20 si=1;resetn=1;
        #10 si=0;
        #10 si=1;
        #10 si=1;
        #10 si=1;
        #10 si=1;
        #10 si=0;
        #10 si=0;
        #10 si=0;
        #10 si=1;
        #10 si=1;

        $finish;
    end
endmodule

devQn1/hello_tb.vcd
$date
	Wed Nov 05 01:02:36 2025
$end
$version
	Icarus Verilog
$end
$timescale
	1ns
$end
$scope module hello_tb $end
$var wire 1 ! y $end
$var wire 1 " so $end
$var wire 4 # po [3:0] $end
$var reg 1 $ clk $end
$var reg 1 % resetn $end
$var reg 1 & si $end
$scope module Q1 $end
$var wire 1 $ clk $end
$var wire 4 ' po [3:0] $end
$var wire 1 % resetn $end
$var wire 1 & si $end
$var wire 1 ! y $end
$var wire 4 ( temp [3:0] $end
$var wire 1 " so $end
$scope module d0 $end
$var wire 1 $ clk $end
$var wire 1 ) d $end
$var wire 1 % resetn $end
$var reg 1 * q $end
$upscope $end
$scope module d1 $end
$var wire 1 $ clk $end
$var wire 1 + d $end
$var wire 1 % resetn $end
$var reg 1 , q $end
$upscope $end
$scope module d2 $end
$var wire 1 $ clk $end
$var wire 1 - d $end
$var wire 1 % resetn $end
$var reg 1 . q $end
$upscope $end
$scope module d3 $end
$var wire 1 $ clk $end
$var wire 1 & d $end
$var wire 1 % resetn $end
$var reg 1 / q $end
$upscope $end
$upscope $end
$upscope $end
$enddefinitions $end
$comment Show the parameter values. $end
$dumpall
$end
#0
$dumpvars
0/
0.
0-
0,
0+
0*
0)
b0 (
b0 '
x&
0%
0$
b0 #
0"
1!
$end
#5
1$
#10
0$
#15
1$
#20
0$
1%
1&
#25
1-
b1000 #
b1000 '
b1000 (
1/
1$
#30
0$
0&
#35
0-
1+
0/
b100 #
b100 '
b100 (
1.
1$
#40
0$
1&
#45
0!
1)
0+
1-
1,
0.
b1010 #
b1010 '
b1010 (
1/
1$
#50
0$
#55
1+
0)
1"
1.
0,
b1101 #
b1101 '
b1101 (
1*
1$
#60
0$
#65
0"
1)
0*
b1110 #
b1110 '
b1110 (
1,
1$
#70
0$
#75
1"
b1111 #
b1111 '
b1111 (
1*
1$
#80
0$
0&
#85
1!
0-
b111 #
b111 '
b111 (
0/
1$
#90
0$
#95
0+
b11 #
b11 '
b11 (
0.
1$
#100
0$
#105
0)
b1 #
b1 '
b1 (
0,
1$
#110
0$
1&
#115
1-
0"
1/
b1000 #
b1000 '
b1000 (
0*
1$
