counter/JohnsonCounter/dflipflop.v
module dflipflop(q, d, clk, resetn, startingvalue);
    input d, clk, resetn, startingvalue;
    output reg q;

    always @(posedge clk or negedge resetn) begin
        if (~resetn)
            q <= startingvalue;
        else
            q <= d;
    end
endmodule

counter/JohnsonCounter/hello.v
module hello(q, clk, resetn);
    input clk, resetn;
    output [3:0] q;
    wire [3:0] d;

    assign d[3] = ~q[0];
    assign d[2] = q[3];
    assign d[1] = q[2];
    assign d[0] = q[1];

    dflipflop D0(q[0], d[0], clk, resetn, 1'b0);
    dflipflop D1(q[1], d[1], clk, resetn, 1'b0);
    dflipflop D2(q[2], d[2], clk, resetn, 1'b0);
    dflipflop D3(q[3], d[3], clk, resetn, 1'b0);
endmodule

counter/JohnsonCounter/hello_tb.v
`timescale 1ns/1ns
`include "dflipflop.v"
`include "hello.v"

module hello_tb;
    reg clk, resetn;
    wire [3:0] q;

    hello uut(q, clk, resetn);

    initial begin
        clk = 0;
        forever #5 clk = ~clk;
    end

    // Stimulus
    initial begin
        $dumpfile("hello_tb.vcd");
        $dumpvars(0, hello_tb);

        resetn = 0;   
        #10 resetn = 1; 

        #200;
        $finish;
    end
endmodule

counter/JohnsonCounter/hello_tb.vcd
$date
	Tue Nov 04 22:56:58 2025
$end
$version
	Icarus Verilog
$end
$timescale
	1ns
$end
$scope module hello_tb $end
$var wire 4 ! q [3:0] $end
$var reg 1 " clk $end
$var reg 1 # resetn $end
$scope module uut $end
$var wire 1 " clk $end
$var wire 1 # resetn $end
$var wire 4 $ q [3:0] $end
$var wire 4 % d [3:0] $end
$scope module D0 $end
$var wire 1 " clk $end
$var wire 1 & d $end
$var wire 1 # resetn $end
$var wire 1 ' startingvalue $end
$var reg 1 ( q $end
$upscope $end
$scope module D1 $end
$var wire 1 " clk $end
$var wire 1 ) d $end
$var wire 1 # resetn $end
$var wire 1 * startingvalue $end
$var reg 1 + q $end
$upscope $end
$scope module D2 $end
$var wire 1 " clk $end
$var wire 1 , d $end
$var wire 1 # resetn $end
$var wire 1 - startingvalue $end
$var reg 1 . q $end
$upscope $end
$scope module D3 $end
$var wire 1 " clk $end
$var wire 1 / d $end
$var wire 1 # resetn $end
$var wire 1 0 startingvalue $end
$var reg 1 1 q $end
$upscope $end
$upscope $end
$upscope $end
$enddefinitions $end
$comment Show the parameter values. $end
$dumpall
$end
#0
$dumpvars
01
00
1/
0.
0-
0,
0+
0*
0)
0(
0'
0&
b1000 %
b0 $
0#
0"
b0 !
$end
#5
1"
#10
0"
1#
#15
1,
b1100 %
b1000 !
b1000 $
11
1"
#20
0"
#25
1)
b1110 %
b1100 !
b1100 $
1.
1"
#30
0"
#35
1&
b1111 %
b1110 !
b1110 $
1+
1"
#40
0"
#45
0/
b111 %
b1111 !
b1111 $
1(
1"
#50
0"
#55
0,
b11 %
b111 !
b111 $
01
1"
#60
0"
#65
0)
b1 %
b11 !
b11 $
0.
1"
#70
0"
#75
0&
b0 %
b1 !
b1 $
0+
1"
#80
0"
#85
1/
b1000 %
b0 !
b0 $
0(
1"
#90
0"
#95
1,
b1100 %
b1000 !
b1000 $
11
1"
#100
0"
#105
1)
b1110 %
b1100 !
b1100 $
1.
1"
#110
0"
#115
1&
b1111 %
b1110 !
b1110 $
1+
1"
#120
0"
#125
0/
b111 %
b1111 !
b1111 $
1(
1"
#130
0"
#135
0,
b11 %
b111 !
b111 $
01
1"
#140
0"
#145
0)
b1 %
b11 !
b11 $
0.
1"
#150
0"
#155
0&
b0 %
b1 !
b1 $
0+
1"
#160
0"
#165
1/
b1000 %
b0 !
b0 $
0(
1"
#170
0"
#175
1,
b1100 %
b1000 !
b1000 $
11
1"
#180
0"
#185
1)
b1110 %
b1100 !
b1100 $
1.
1"
#190
0"
#195
1&
b1111 %
b1110 !
b1110 $
1+
1"
#200
0"
#205
0/
b111 %
b1111 !
b1111 $
1(
1"
