difficultQn2/jkflipflop.v
module jkflipflop(
    input j, k, clk, reset,
    output reg q
);
    always @(posedge clk or posedge reset) begin
        if (reset)
            q <= 0;
        else begin
            case ({j, k})
                2'b00: q <= q;       // hold
                2'b01: q <= 0;       // reset
                2'b10: q <= 1;       // set
                2'b11: q <= ~q;      // toggle
            endcase
        end
    end
endmodule

difficultQn2/hello.v
module hello(
    input clk,
    input reset,
    output [4:0] q,
    output flag
);
    wire q0, q1, q2, q3, q4;
    wire flag_ff;

    wire count17 = q4 & ~q3 & ~q2 & ~q1 & q0;

    jkflipflop FF0(.j(1'b1), .k(1'b1), .clk(clk), .reset(reset | count17), .q(q0));
    jkflipflop FF1(.j(q0), .k(q0), .clk(clk), .reset(reset | count17), .q(q1));
    jkflipflop FF2(.j(q1 & q0), .k(q1 & q0), .clk(clk), .reset(reset | count17), .q(q2));
    jkflipflop FF3(.j(q2 & q1 & q0), .k(q2 & q1 & q0), .clk(clk), .reset(reset | count17), .q(q3));
    jkflipflop FF4(.j(q3 & q2 & q1 & q0), .k(q3 & q2 & q1 & q0), .clk(clk), .reset(reset | count17), .q(q4));

    assign q = {q4, q3, q2, q1, q0};

    wire count_ge8 = q3 | (q4);  
    jkflipflop FLAG(.j(count_ge8), .k(count_ge8), .clk(clk), .reset(reset), .q(flag_ff));

    assign flag = flag_ff;
endmodule

difficultQn2/hello_tb.v
`timescale 1ns/1ns
`include "jkflipflop.v"
`include "hello.v"

module hello_tb();
    reg clk, reset;
    wire [4:0] q;
    wire flag;

    hello U1(clk, reset, q, flag);

    initial begin
    clk = 0;
    forever #5 clk = ~clk; 
    end

    initial begin
        $dumpfile("hello_tb.vcd");
        $dumpvars(0, hello_tb);

        reset = 1;
        #10 reset = 0;  

        #500 $finish; 
    end
endmodule

difficultQn2/hello_tb.vcd
$date
	Wed Nov 05 10:22:49 2025
$end
$version
	Icarus Verilog
$end
$timescale
	1ns
$end
$scope module hello_tb $end
$var wire 5 ! q [4:0] $end
$var wire 1 " flag $end
$var reg 1 # clk $end
$var reg 1 $ reset $end
$scope module U1 $end
$var wire 1 # clk $end
$var wire 1 % count17 $end
$var wire 1 & count_ge8 $end
$var wire 1 " flag $end
$var wire 1 $ reset $end
$var wire 1 ' q4 $end
$var wire 1 ( q3 $end
$var wire 1 ) q2 $end
$var wire 1 * q1 $end
$var wire 1 + q0 $end
$var wire 5 , q [4:0] $end
$var wire 1 - flag_ff $end
$scope module FF0 $end
$var wire 1 # clk $end
$var wire 1 . j $end
$var wire 1 / k $end
$var wire 1 0 reset $end
$var reg 1 + q $end
$upscope $end
$scope module FF1 $end
$var wire 1 # clk $end
$var wire 1 + j $end
$var wire 1 + k $end
$var wire 1 1 reset $end
$var reg 1 * q $end
$upscope $end
$scope module FF2 $end
$var wire 1 # clk $end
$var wire 1 2 j $end
$var wire 1 3 k $end
$var wire 1 4 reset $end
$var reg 1 ) q $end
$upscope $end
$scope module FF3 $end
$var wire 1 # clk $end
$var wire 1 5 j $end
$var wire 1 6 k $end
$var wire 1 7 reset $end
$var reg 1 ( q $end
$upscope $end
$scope module FF4 $end
$var wire 1 # clk $end
$var wire 1 8 j $end
$var wire 1 9 k $end
$var wire 1 : reset $end
$var reg 1 ' q $end
$upscope $end
$scope module FLAG $end
$var wire 1 # clk $end
$var wire 1 & j $end
$var wire 1 & k $end
$var wire 1 $ reset $end
$var reg 1 - q $end
$upscope $end
$upscope $end
$upscope $end
$enddefinitions $end
$comment Show the parameter values. $end
$dumpall
$end
#0
$dumpvars
1:
09
08
17
06
05
14
03
02
11
10
1/
1.
0-
b0 ,
0+
0*
0)
0(
0'
0&
0%
1$
0#
0"
b0 !
$end
#5
1#
#10
00
01
04
07
0:
0#
0$
#15
b1 !
b1 ,
1+
1#
#20
0#
#25
0+
b10 !
b10 ,
1*
1#
#30
0#
#35
13
12
b11 !
b11 ,
1+
1#
#40
0#
#45
03
02
0+
0*
b100 !
b100 ,
1)
1#
#50
0#
#55
b101 !
b101 ,
1+
1#
#60
0#
#65
0+
b110 !
b110 ,
1*
1#
#70
0#
#75
16
15
13
12
b111 !
b111 ,
1+
1#
#80
0#
#85
06
05
03
02
1&
0+
0*
0)
b1000 !
b1000 ,
1(
1#
#90
0#
#95
b1001 !
b1001 ,
1+
1"
1-
1#
#100
0#
#105
0+
b1010 !
b1010 ,
1*
0"
0-
1#
#110
0#
#115
13
12
b1011 !
b1011 ,
1+
1"
1-
1#
#120
0#
#125
03
02
0+
0*
b1100 !
b1100 ,
1)
0"
0-
1#
#130
0#
#135
b1101 !
b1101 ,
1+
1"
1-
1#
#140
0#
#145
0+
b1110 !
b1110 ,
1*
0"
0-
1#
#150
0#
#155
19
18
16
15
13
12
b1111 !
b1111 ,
1+
1"
1-
1#
#160
0#
#165
09
08
06
05
03
02
0+
0*
0)
0(
b10000 !
b10000 ,
1'
0"
0-
1#
#170
0#
#175
0&
0'
00
01
04
07
0:
0%
b0 !
b0 ,
0+
1"
1-
1#
#180
0#
#185
b1 !
b1 ,
1+
1#
#190
0#
#195
0+
b10 !
b10 ,
1*
1#
#200
0#
#205
13
12
b11 !
b11 ,
1+
1#
#210
0#
#215
03
02
0+
0*
b100 !
b100 ,
1)
1#
#220
0#
#225
b101 !
b101 ,
1+
1#
#230
0#
#235
0+
b110 !
b110 ,
1*
1#
#240
0#
#245
16
15
13
12
b111 !
b111 ,
1+
1#
#250
0#
#255
06
05
03
02
1&
0+
0*
0)
b1000 !
b1000 ,
1(
1#
#260
0#
#265
b1001 !
b1001 ,
1+
0"
0-
1#
#270
0#
#275
0+
b1010 !
b1010 ,
1*
1"
1-
1#
#280
0#
#285
13
12
b1011 !
b1011 ,
1+
0"
0-
1#
#290
0#
#295
03
02
0+
0*
b1100 !
b1100 ,
1)
1"
1-
1#
#300
0#
#305
b1101 !
b1101 ,
1+
0"
0-
1#
#310
0#
#315
0+
b1110 !
b1110 ,
1*
1"
1-
1#
#320
0#
#325
19
18
16
15
13
12
b1111 !
b1111 ,
1+
0"
0-
1#
#330
0#
#335
09
08
06
05
03
02
0+
0*
0)
0(
b10000 !
b10000 ,
1'
1"
1-
1#
#340
0#
#345
0&
0'
00
01
04
07
0:
0%
b0 !
b0 ,
0+
0"
0-
1#
#350
0#
#355
b1 !
b1 ,
1+
1#
#360
0#
#365
0+
b10 !
b10 ,
1*
1#
#370
0#
#375
13
12
b11 !
b11 ,
1+
1#
#380
0#
#385
03
02
0+
0*
b100 !
b100 ,
1)
1#
#390
0#
#395
b101 !
b101 ,
1+
1#
#400
0#
#405
0+
b110 !
b110 ,
1*
1#
#410
0#
#415
16
15
13
12
b111 !
b111 ,
1+
1#
#420
0#
#425
06
05
03
02
1&
0+
0*
0)
b1000 !
b1000 ,
1(
1#
#430
0#
#435
b1001 !
b1001 ,
1+
1"
1-
1#
#440
0#
#445
0+
b1010 !
b1010 ,
1*
0"
0-
1#
#450
0#
#455
13
12
b1011 !
b1011 ,
1+
1"
1-
1#
#460
0#
#465
03
02
0+
0*
b1100 !
b1100 ,
1)
0"
0-
1#
#470
0#
#475
b1101 !
b1101 ,
1+
1"
1-
1#
#480
0#
#485
0+
b1110 !
b1110 ,
1*
0"
0-
1#
#490
0#
#495
19
18
16
15
13
12
b1111 !
b1111 ,
1+
1"
1-
1#
#500
0#
#505
09
08
06
05
03
02
0+
0*
0)
0(
b10000 !
b10000 ,
1'
0"
0-
1#
